LICENCE.txt
MANIFEST.in
README.rst
setup.py
Astrodb.egg-info/PKG-INFO
Astrodb.egg-info/SOURCES.txt
Astrodb.egg-info/dependency_links.txt
Astrodb.egg-info/entry_points.txt
Astrodb.egg-info/not-zip-safe
Astrodb.egg-info/requires.txt
Astrodb.egg-info/top_level.txt
astrodb/__init__.py
astrodb/console_script.py
astrodb/queries.py