Metadata-Version: 1.1
Name: Astrodb
Version: 0.1.5
Summary: 
